README.rst
setup.py
systempay/__init__.py
systempay/client.py
systempay/exceptions.py
systempay/networks.py
systempay/tests.py
systempay/utils.py
systempay.egg-info/PKG-INFO
systempay.egg-info/SOURCES.txt
systempay.egg-info/dependency_links.txt
systempay.egg-info/requires.txt
systempay.egg-info/top_level.txt
systempay/codes/__init__.py
systempay/codes/error.py
systempay/codes/extended.py
systempay/codes/transaction.py