Metadata-Version: 1.1
Name: systempay
Version: 0.0.12
Summary: Systempay API Client
Home-page: UNKNOWN
Author: Jurismarchés
Author-email: contact@jurismarches.com
License: UNKNOWN
Platform: UNKNOWN
Classifier: Development Status :: 4 - Beta
Classifier: License :: OSI Approved :: MIT License
Classifier: Intended Audience :: Developers
Classifier: Topic :: Office/Business :: Financial
Classifier: Programming Language :: Python
Classifier: Programming Language :: Python :: 3
